LICENSE
recursive_validator/__init__.py
recursive_validator/helpers/data_helpers.py
recursive_validator/helpers/file_helpers.py
recursive_validator/helpers/log_helpers.py
recursive_validator/recursive_validator.py
recursive_validator-0.0.215.dist-info/LICENSE
recursive_validator-0.0.215.dist-info/METADATA
recursive_validator-0.0.215.dist-info/WHEEL
recursive_validator-0.0.215.dist-info/entry_points.txt
recursive_validator-0.0.215.dist-info/RECORD
