Metadata-Version: 2.1
Name: recursive-validator
Version: 0.0.215
Summary: 
Home-page: https://github.com/fsai-dev/fsai-cli-tools
License: MIT
Author: Michael Mohamed
Author-email: michael@foundationstack.com
Requires-Python: >=3.7,<4.0
Classifier: License :: OSI Approved :: MIT License
Classifier: Programming Language :: Python :: 3
Classifier: Programming Language :: Python :: 3.7
Classifier: Programming Language :: Python :: 3.8
Classifier: Programming Language :: Python :: 3.9
Classifier: Programming Language :: Python :: 3.10
Classifier: Programming Language :: Python :: 3.11
Classifier: Programming Language :: Python :: 3.12
Requires-Dist: PyYAML (>=6.0,<7.0)
Requires-Dist: beartype (>=0.10.4,<0.11.0)
Requires-Dist: loguru (>=0.6.0,<0.7.0)
Project-URL: Repository, https://github.com/fsai-dev/fsai-cli-tools
